pyqtcountrypicker/__init__.py
pyqtcountrypicker/countries.py
pyqtcountrypicker/country_picker.py
pyqtcountrypicker/flags/ad.png
pyqtcountrypicker/flags/ae.png
pyqtcountrypicker/flags/af.png
pyqtcountrypicker/flags/ag.png
pyqtcountrypicker/flags/ai.png
pyqtcountrypicker/flags/al.png
pyqtcountrypicker/flags/am.png
pyqtcountrypicker/flags/ao.png
pyqtcountrypicker/flags/ar.png
pyqtcountrypicker/flags/as.png
pyqtcountrypicker/flags/at.png
pyqtcountrypicker/flags/au.png
pyqtcountrypicker/flags/aw.png
pyqtcountrypicker/flags/az.png
pyqtcountrypicker/flags/ba.png
pyqtcountrypicker/flags/bb.png
pyqtcountrypicker/flags/bd.png
pyqtcountrypicker/flags/be.png
pyqtcountrypicker/flags/bf.png
pyqtcountrypicker/flags/bg.png
pyqtcountrypicker/flags/bh.png
pyqtcountrypicker/flags/bi.png
pyqtcountrypicker/flags/bj.png
pyqtcountrypicker/flags/bl.png
pyqtcountrypicker/flags/bm.png
pyqtcountrypicker/flags/bn.png
pyqtcountrypicker/flags/bo.png
pyqtcountrypicker/flags/bq.png
pyqtcountrypicker/flags/br.png
pyqtcountrypicker/flags/bs.png
pyqtcountrypicker/flags/bt.png
pyqtcountrypicker/flags/bw.png
pyqtcountrypicker/flags/by.png
pyqtcountrypicker/flags/bz.png
pyqtcountrypicker/flags/ca.png
pyqtcountrypicker/flags/cd.png
pyqtcountrypicker/flags/cf.png
pyqtcountrypicker/flags/cg.png
pyqtcountrypicker/flags/ch.png
pyqtcountrypicker/flags/ci.png
pyqtcountrypicker/flags/ck.png
pyqtcountrypicker/flags/cl.png
pyqtcountrypicker/flags/cm.png
pyqtcountrypicker/flags/cn.png
pyqtcountrypicker/flags/co.png
pyqtcountrypicker/flags/cr.png
pyqtcountrypicker/flags/cu.png
pyqtcountrypicker/flags/cv.png
pyqtcountrypicker/flags/cw.png
pyqtcountrypicker/flags/cy.png
pyqtcountrypicker/flags/cz.png
pyqtcountrypicker/flags/de.png
pyqtcountrypicker/flags/dj.png
pyqtcountrypicker/flags/dk.png
pyqtcountrypicker/flags/dm.png
pyqtcountrypicker/flags/do.png
pyqtcountrypicker/flags/dz.png
pyqtcountrypicker/flags/ec.png
pyqtcountrypicker/flags/ee.png
pyqtcountrypicker/flags/eg.png
pyqtcountrypicker/flags/er.png
pyqtcountrypicker-1.0.1.dist-info/LICENSE
pyqtcountrypicker-1.0.1.dist-info/METADATA
pyqtcountrypicker-1.0.1.dist-info/WHEEL
pyqtcountrypicker-1.0.1.dist-info/entry_points.txt
pyqtcountrypicker-1.0.1.dist-info/top_level.txt
pyqtcountrypicker-1.0.1.dist-info/RECORD
