Metadata-Version: 2.1
Name: pyqtcountrypicker
Version: 1.0.1
Summary: A simple, yet highly customizable country picker widget for PyQt and PySide
Home-page: https://github.com/niklashenning/pyqtcountrypicker
Author: Niklas Henning
Author-email: business@niklashenning.com
License: MIT
Keywords: python,pyqt,pyside,qt,country-picker
Classifier: Programming Language :: Python :: 3
Classifier: Operating System :: OS Independent
Classifier: License :: OSI Approved :: MIT License
Requires-Python: >=3.7
License-File: LICENSE
Requires-Dist: QtPy >=2.4.1
